LICENSE.txt
README.md
setup.py
src/pmb_py/__init__.py
src/pmb_py/api.py
src/pmb_py/core.py
src/pmb_py/spec.py
src/pmb_py.egg-info/PKG-INFO
src/pmb_py.egg-info/SOURCES.txt
src/pmb_py.egg-info/dependency_links.txt
src/pmb_py.egg-info/requires.txt
src/pmb_py.egg-info/top_level.txt
src/pmb_py/adapter/__init__.py
src/pmb_py/adapter/pmb_convert.py
src/pmb_py/domain/__init__.py
src/pmb_py/domain/model.py
src/pmb_py/domain/query_result.py
tests/test_block_curd.py
tests/test_gantt_item_curd.py
tests/test_member_curd.py
tests/test_pmb_gantt_api.py
tests/test_pmb_login.py
tests/test_project_curd.py
tests/test_project_params.py
tests/test_task_curd.py
tests/test_taskgroup_curd.py