Metadata-Version: 2.1
Name: pmb-py
Version: 0.4.4.0
Summary: pmb restful api python wrap
Home-page: https://github.com/MoonShineVFX/pmb_py_api
Author: Noflame.lin
Author-email: linjuang@gmail.com
Classifier: Programming Language :: Python :: 3.6
Classifier: Operating System :: OS Independent
Requires-Python: >=3.6
License-File: LICENSE.txt
Requires-Dist: requests
Requires-Dist: simplejson
